potato_distillery/__init__.py
potato_distillery/distill.py
potato_distillery/utils.py
potato_distillery-0.1.0.dist-info/LICENSE
potato_distillery-0.1.0.dist-info/METADATA
potato_distillery-0.1.0.dist-info/WHEEL
potato_distillery-0.1.0.dist-info/top_level.txt
potato_distillery-0.1.0.dist-info/RECORD
