Metadata-Version: 2.1
Name: potato-distillery
Version: 0.1.0
Summary: A package that distills large ML models.
Home-page: https://github.com/SpyrosMouselinos/potato_distillery
Author: Spyros Mouselinos
Author-email: s.mouselinos@uw.edu.pl
License: UNKNOWN
Platform: UNKNOWN
Classifier: Programming Language :: Python :: 3
Classifier: License :: OSI Approved :: MIT License
Classifier: Operating System :: OS Independent
Requires-Python: >=3.6
License-File: LICENSE
Requires-Dist: torch
Requires-Dist: torchinfo
Requires-Dist: transformers
Requires-Dist: huggingface
